{
  "posts": [
  
  {
    
    "id": 1,
    "Name":"Днiпровсько-Донецький"
    "Region": "Херсонська",
    "Obl": "Каховське-Н"
    "Date": "12.09.1995",
    "Adress": "5 км на ПдС вiд м. Херсон",
    "Date_vved": "1990",
    "Vudob": "6120",
    "Num_sv": "12",
    "sheme": "https://stud.com.ua/htm/img/32/2013/12.png"
    
  },
  {
    
    "id": 3,
    "Region": "Пiдкамiнь",
    "Obl": "04.05.1992",
    "Oil": "86",
    "date": "7",
    "numFuel": "1,16",
    "numDizFuel": "0,0",
    "numOil": "0,1"
    
  },
  {
    
    "id": 4, 
    "Region": "Насташино",
    "Obl": "04.05.1992",
    "Oil": "44",
    "date": "7",
    "numFuel": "1,16",
    "numDizFuel": "0,2",
    "numOil": "0,9"
    
  },
  {
    
    "id": 5,
    "Region": "Куропатники",
    "Obl": "01.02.1992",
    "Oil": "120",
    "date": "7",
    "numFuel": "1,84",
    "numDizFuel": "0,0",
    "numOil": "0,7"
    
  }
    
  ]
}
